{
  "version": "1.1.0",
  "diagrams": [
    {
      "ordinal": 0,
      "scrollPosition": {
        "x": 0,
        "y": 0
      },
      "nodes": [
        {
          "location": {
            "x": 1480.217844146536,
            "y": 361.37672812963939
          },
          "nodeIndex": "Metrics",
          "nodeLineageTag": "27e469b5-1aa2-4876-bbec-b33d0519e1aa",
          "size": {
            "height": 152,
            "width": 234
          },
          "zIndex": 14
        },
        {
          "location": {
            "x": 1764.217844146536,
            "y": 289.37672812963939
          },
          "nodeIndex": "circuits",
          "nodeLineageTag": "332a1383-026d-477a-8a8e-29ed796f02dd",
          "size": {
            "height": 296,
            "width": 234
          },
          "zIndex": 0
        },
        {
          "location": {
            "x": 1123.7082217060192,
            "y": 375.53029792177171
          },
          "nodeIndex": "constructor_results",
          "nodeLineageTag": "a07897a9-30b9-4841-a91e-b1336d0c457f",
          "size": {
            "height": 200,
            "width": 234
          },
          "zIndex": 0
        },
        {
          "location": {
            "x": 1246.217844146536,
            "y": -17.297242935747022
          },
          "nodeIndex": "constructor_standings",
          "nodeLineageTag": "2c188631-e392-49b3-96d1-2daa36139ce9",
          "size": {
            "height": 248,
            "width": 234
          },
          "zIndex": 0
        },
        {
          "location": {
            "x": 959.15511080007821,
            "y": 122.83350392024033
          },
          "nodeIndex": "constructors",
          "nodeLineageTag": "3cdb2cb3-5dab-4afe-884e-084c27747746",
          "size": {
            "height": 200,
            "width": 234
          },
          "zIndex": 0
        },
        {
          "location": {
            "x": 100.95079911645848,
            "y": 576.75345625927866
          },
          "nodeIndex": "driver_standings",
          "nodeLineageTag": "d925ba47-86d4-4443-813f-0fe12f46c585",
          "size": {
            "height": 248,
            "width": 234
          },
          "zIndex": 0
        },
        {
          "location": {
            "x": 387.59743770517639,
            "y": 227.35277273726194
          },
          "nodeIndex": "drivers",
          "nodeLineageTag": "2e23f43e-b021-4646-b80a-fc18437b8291",
          "size": {
            "height": 296,
            "width": 234
          },
          "zIndex": 0
        },
        {
          "location": {
            "x": 337.03862868307738,
            "y": -50
          },
          "nodeIndex": "lap_times",
          "nodeLineageTag": "ecd1567e-b13c-4b06-8176-69c265faa332",
          "size": {
            "height": 224,
            "width": 234
          },
          "zIndex": 0
        },
        {
          "location": {
            "x": 50,
            "y": 200.26086740649919
          },
          "nodeIndex": "pit_stops (2)",
          "nodeLineageTag": "1cfa5f96-813a-49ff-a9ea-48a8766e1d2e",
          "size": {
            "height": 248,
            "width": 234
          },
          "zIndex": 0
        },
        {
          "location": {
            "x": 673.94013536197531,
            "y": 204.55851015490811
          },
          "nodeIndex": "qualifying",
          "nodeLineageTag": "75deb5d8-ce89-4cfc-9e22-153809ee1abb",
          "size": {
            "height": 296,
            "width": 234
          },
          "zIndex": 0
        },
        {
          "location": {},
          "nodeIndex": "races",
          "nodeLineageTag": "b89bce72-e6f1-468b-8476-26a5f81f8b0c",
          "size": {
            "height": 300,
            "width": 234
          },
          "zIndex": 0
        }
      ],
      "name": "All tables",
      "zoomValue": 43.012397579589766,
      "pinKeyFieldsToTop": false,
      "showExtraHeaderInfo": false,
      "hideKeyFieldsWhenCollapsed": false,
      "tablesLocked": false
    }
  ],
  "selectedDiagram": "All tables",
  "defaultDiagram": "All tables"
}